conjugator/__init__.py
conjugator/spanish.py
conjugator-1.1.1.dist-info/AUTHORS.rst
conjugator-1.1.1.dist-info/LICENSE.txt
conjugator-1.1.1.dist-info/METADATA
conjugator-1.1.1.dist-info/WHEEL
conjugator-1.1.1.dist-info/top_level.txt
conjugator-1.1.1.dist-info/RECORD
