Metadata-Version: 2.1
Name: conjugator
Version: 1.1.1
Summary: Add a short description here!
Home-page: https://github.com/plysytsya/conjugator
Author: Pavlo Lysytsya
Author-email: pavlo.lysytsya@gmail.com
License: mit
Project-URL: Documentation, https://github.com/plysytsya/conjugator
Platform: any
Classifier: Development Status :: 4 - Beta
Classifier: Programming Language :: Python
Requires-Dist: requests
Requires-Dist: beautifulsoup4
Requires-Dist: pandas
Requires-Dist: pytest-xdist
Provides-Extra: testing
Requires-Dist: pytest ; extra == 'testing'
Requires-Dist: pytest-cov ; extra == 'testing'
